{
  "items": [
    {
      "track": {
        "album": {
          "album_type": "album",
          "artists": [
            {
              "external_urls": {
                "spotify": "https://open.spotify.com/artist/5L1lO4eRHmJ7a0Q6csE5cT"
              },
              "href": "https://api.spotify.com/v1/artists/5L1lO4eRHmJ7a0Q6csE5cT",
              "id": "5L1lO4eRHmJ7a0Q6csE5cT",
              "name": "LISA",
              "type": "artist",
              "uri": "spotify:artist:5L1lO4eRHmJ7a0Q6csE5cT"
            }
          ],
          "available_markets": [
            "AR",
            "AU",
            "AT",
            "BE",
            "BO",
            "BR",
            "BG",
            "CA",
            "CL",
            "CO",
            "CR",
            "CY",
            "CZ",
            "DK",
            "DO",
            "DE",
            "EC",
            "EE",
            "SV",
            "FI",
            "FR",
            "GR",
            "GT",
            "HN",
            "HK",
            "HU",
            "IS",
            "IE",
            "IT",
            "LV",
            "LT",
            "LU",
            "MY",
            "MT",
            "MX",
            "NL",
            "NZ",
            "NI",
            "NO",
            "PA",
            "PY",
            "PE",
            "PH",
            "PL",
            "PT",
            "SG",
            "SK",
            "ES",
            "SE",
            "CH",
            "TW",
            "TR",
            "UY",
            "US",
            "GB",
            "AD",
            "LI",
            "MC",
            "ID",
            "JP",
            "TH",
            "VN",
            "RO",
            "IL",
            "ZA",
            "SA",
            "AE",
            "BH",
            "QA",
            "OM",
            "KW",
            "EG",
            "MA",
            "DZ",
            "TN",
            "LB",
            "JO",
            "PS",
            "IN",
            "BY",
            "KZ",
            "MD",
            "UA",
            "AL",
            "BA",
            "HR",
            "ME",
            "MK",
            "RS",
            "SI",
            "KR",
            "BD",
            "PK",
            "LK",
            "GH",
            "KE",
            "NG",
            "TZ",
            "UG",
            "AG",
            "AM",
            "BS",
            "BB",
            "BZ",
            "BT",
            "BW",
            "BF",
            "CV",
            "CW",
            "DM",
            "FJ",
            "GM",
            "GE",
            "GD",
            "GW",
            "GY",
            "HT",
            "JM",
            "KI",
            "LS",
            "LR",
            "MW",
            "MV",
            "ML",
            "MH",
            "FM",
            "NA",
            "NR",
            "NE",
            "PW",
            "PG",
            "PR",
            "WS",
            "SM",
            "ST",
            "SN",
            "SC",
            "SL",
            "SB",
            "KN",
            "LC",
            "VC",
            "SR",
            "TL",
            "TO",
            "TT",
            "TV",
            "VU",
            "AZ",
            "BN",
            "BI",
            "KH",
            "CM",
            "TD",
            "KM",
            "GQ",
            "SZ",
            "GA",
            "GN",
            "KG",
            "LA",
            "MO",
            "MR",
            "MN",
            "NP",
            "RW",
            "TG",
            "UZ",
            "ZW",
            "BJ",
            "MG",
            "MU",
            "MZ",
            "AO",
            "CI",
            "DJ",
            "ZM",
            "CD",
            "CG",
            "IQ",
            "LY",
            "TJ",
            "VE",
            "ET",
            "XK"
          ],
          "external_urls": {
            "spotify": "https://open.spotify.com/album/5eoWRkeplmcCL97afSMJVm"
          },
          "href": "https://api.spotify.com/v1/albums/5eoWRkeplmcCL97afSMJVm",
          "id": "5eoWRkeplmcCL97afSMJVm",
          "images": [
            {
              "height": 640,
              "url": "https://i.scdn.co/image/ab67616d0000b2738034090e4afb5b053cd3e067",
              "width": 640
            },
            {
              "height": 300,
              "url": "https://i.scdn.co/image/ab67616d00001e028034090e4afb5b053cd3e067",
              "width": 300
            },
            {
              "height": 64,
              "url": "https://i.scdn.co/image/ab67616d000048518034090e4afb5b053cd3e067",
              "width": 64
            }
          ],
          "name": "Alter Ego",
          "release_date": "2025-02-28",
          "release_date_precision": "day",
          "total_tracks": 15,
          "type": "album",
          "uri": "spotify:album:5eoWRkeplmcCL97afSMJVm"
        },
        "artists": [
          {
            "external_urls": {
              "spotify": "https://open.spotify.com/artist/5L1lO4eRHmJ7a0Q6csE5cT"
            },
            "href": "https://api.spotify.com/v1/artists/5L1lO4eRHmJ7a0Q6csE5cT",
            "id": "5L1lO4eRHmJ7a0Q6csE5cT",
            "name": "LISA",
            "type": "artist",
            "uri": "spotify:artist:5L1lO4eRHmJ7a0Q6csE5cT"
          },
          {
            "external_urls": {
              "spotify": "https://open.spotify.com/artist/181bsRPaVXVlUKXrxwZfHK"
            },
            "href": "https://api.spotify.com/v1/artists/181bsRPaVXVlUKXrxwZfHK",
            "id": "181bsRPaVXVlUKXrxwZfHK",
            "name": "Megan Thee Stallion",
            "type": "artist",
            "uri": "spotify:artist:181bsRPaVXVlUKXrxwZfHK"
          }
        ],
        "available_markets": [
          "AR",
          "AU",
          "AT",
          "BE",
          "BO",
          "BR",
          "BG",
          "CA",
          "CL",
          "CO",
          "CR",
          "CY",
          "CZ",
          "DK",
          "DO",
          "DE",
          "EC",
          "EE",
          "SV",
          "FI",
          "FR",
          "GR",
          "GT",
          "HN",
          "HK",
          "HU",
          "IS",
          "IE",
          "IT",
          "LV",
          "LT",
          "LU",
          "MY",
          "MT",
          "MX",
          "NL",
          "NZ",
          "NI",
          "NO",
          "PA",
          "PY",
          "PE",
          "PH",
          "PL",
          "PT",
          "SG",
          "SK",
          "ES",
          "SE",
          "CH",
          "TW",
          "TR",
          "UY",
          "US",
          "GB",
          "AD",
          "LI",
          "MC",
          "ID",
          "JP",
          "TH",
          "VN",
          "RO",
          "IL",
          "ZA",
          "SA",
          "AE",
          "BH",
          "QA",
          "OM",
          "KW",
          "EG",
          "MA",
          "DZ",
          "TN",
          "LB",
          "JO",
          "PS",
          "IN",
          "BY",
          "KZ",
          "MD",
          "UA",
          "AL",
          "BA",
          "HR",
          "ME",
          "MK",
          "RS",
          "SI",
          "KR",
          "BD",
          "PK",
          "LK",
          "GH",
          "KE",
          "NG",
          "TZ",
          "UG",
          "AG",
          "AM",
          "BS",
          "BB",
          "BZ",
          "BT",
          "BW",
          "BF",
          "CV",
          "CW",
          "DM",
          "FJ",
          "GM",
          "GE",
          "GD",
          "GW",
          "GY",
          "HT",
          "JM",
          "KI",
          "LS",
          "LR",
          "MW",
          "MV",
          "ML",
          "MH",
          "FM",
          "NA",
          "NR",
          "NE",
          "PW",
          "PG",
          "PR",
          "WS",
          "SM",
          "ST",
          "SN",
          "SC",
          "SL",
          "SB",
          "KN",
          "LC",
          "VC",
          "SR",
          "TL",
          "TO",
          "TT",
          "TV",
          "VU",
          "AZ",
          "BN",
          "BI",
          "KH",
          "CM",
          "TD",
          "KM",
          "GQ",
          "SZ",
          "GA",
          "GN",
          "KG",
          "LA",
          "MO",
          "MR",
          "MN",
          "NP",
          "RW",
          "TG",
          "UZ",
          "ZW",
          "BJ",
          "MG",
          "MU",
          "MZ",
          "AO",
          "CI",
          "DJ",
          "ZM",
          "CD",
          "CG",
          "IQ",
          "LY",
          "TJ",
          "VE",
          "ET",
          "XK"
        ],
        "disc_number": 1,
        "duration_ms": 165395,
        "explicit": true,
        "external_ids": {
          "isrc": "USRC12500276"
        },
        "external_urls": {
          "spotify": "https://open.spotify.com/track/03qZDQKRYZdjhKsQ5G5H0t"
        },
        "href": "https://api.spotify.com/v1/tracks/03qZDQKRYZdjhKsQ5G5H0t",
        "id": "03qZDQKRYZdjhKsQ5G5H0t",
        "is_local": false,
        "name": "Rapunzel (feat. Megan Thee Stallion)",
        "popularity": 73,
        "preview_url": null,
        "track_number": 7,
        "type": "track",
        "uri": "spotify:track:03qZDQKRYZdjhKsQ5G5H0t"
      },
      "played_at": "2025-03-13T04:43:55.270Z",
      "context": {
        "href": "https://api.spotify.com/v1/playlists/5m4CQQmGnhc9GPz3WWdHuB",
        "external_urls": {
          "spotify": "https://open.spotify.com/playlist/5m4CQQmGnhc9GPz3WWdHuB"
        },
        "type": "playlist",
        "uri": "spotify:playlist:5m4CQQmGnhc9GPz3WWdHuB"
      }
    },
    {
      "track": {
        "album": {
          "album_type": "single",
          "artists": [
            {
              "external_urls": {
                "spotify": "https://open.spotify.com/artist/4gvjmrtzydbMpyJaXUtwvP"
              },
              "href": "https://api.spotify.com/v1/artists/4gvjmrtzydbMpyJaXUtwvP",
              "id": "4gvjmrtzydbMpyJaXUtwvP",
              "name": "Addison Rae",
              "type": "artist",
              "uri": "spotify:artist:4gvjmrtzydbMpyJaXUtwvP"
            }
          ],
          "available_markets": [
            "AR",
            "AU",
            "AT",
            "BE",
            "BO",
            "BR",
            "BG",
            "CA",
            "CL",
            "CO",
            "CR",
            "CY",
            "CZ",
            "DK",
            "DO",
            "DE",
            "EC",
            "EE",
            "SV",
            "FI",
            "FR",
            "GR",
            "GT",
            "HN",
            "HK",
            "HU",
            "IS",
            "IE",
            "IT",
            "LV",
            "LT",
            "LU",
            "MY",
            "MT",
            "MX",
            "NL",
            "NZ",
            "NI",
            "NO",
            "PA",
            "PY",
            "PE",
            "PH",
            "PL",
            "PT",
            "SG",
            "SK",
            "ES",
            "SE",
            "CH",
            "TW",
            "TR",
            "UY",
            "US",
            "GB",
            "AD",
            "LI",
            "MC",
            "ID",
            "JP",
            "TH",
            "VN",
            "RO",
            "IL",
            "ZA",
            "SA",
            "AE",
            "BH",
            "QA",
            "OM",
            "KW",
            "EG",
            "MA",
            "DZ",
            "TN",
            "LB",
            "JO",
            "PS",
            "IN",
            "BY",
            "KZ",
            "MD",
            "UA",
            "AL",
            "BA",
            "HR",
            "ME",
            "MK",
            "RS",
            "SI",
            "KR",
            "BD",
            "PK",
            "LK",
            "GH",
            "KE",
            "NG",
            "TZ",
            "UG",
            "AG",
            "AM",
            "BS",
            "BB",
            "BZ",
            "BT",
            "BW",
            "BF",
            "CV",
            "CW",
            "DM",
            "FJ",
            "GM",
            "GE",
            "GD",
            "GW",
            "GY",
            "HT",
            "JM",
            "KI",
            "LS",
            "LR",
            "MW",
            "MV",
            "ML",
            "MH",
            "FM",
            "NA",
            "NR",
            "NE",
            "PW",
            "PG",
            "PR",
            "WS",
            "SM",
            "ST",
            "SN",
            "SC",
            "SL",
            "SB",
            "KN",
            "LC",
            "VC",
            "SR",
            "TL",
            "TO",
            "TT",
            "TV",
            "VU",
            "AZ",
            "BN",
            "BI",
            "KH",
            "CM",
            "TD",
            "KM",
            "GQ",
            "SZ",
            "GA",
            "GN",
            "KG",
            "LA",
            "MO",
            "MR",
            "MN",
            "NP",
            "RW",
            "TG",
            "UZ",
            "ZW",
            "BJ",
            "MG",
            "MU",
            "MZ",
            "AO",
            "CI",
            "DJ",
            "ZM",
            "CD",
            "CG",
            "IQ",
            "LY",
            "TJ",
            "VE",
            "ET",
            "XK"
          ],
          "external_urls": {
            "spotify": "https://open.spotify.com/album/0XA403JTounqFh2owquBXu"
          },
          "href": "https://api.spotify.com/v1/albums/0XA403JTounqFh2owquBXu",
          "id": "0XA403JTounqFh2owquBXu",
          "images": [
            {
              "height": 640,
              "url": "https://i.scdn.co/image/ab67616d0000b2734e5a5862355a5e953549292b",
              "width": 640
            },
            {
              "height": 300,
              "url": "https://i.scdn.co/image/ab67616d00001e024e5a5862355a5e953549292b",
              "width": 300
            },
            {
              "height": 64,
              "url": "https://i.scdn.co/image/ab67616d000048514e5a5862355a5e953549292b",
              "width": 64
            }
          ],
          "name": "Diet Pepsi",
          "release_date": "2024-08-09",
          "release_date_precision": "day",
          "total_tracks": 1,
          "type": "album",
          "uri": "spotify:album:0XA403JTounqFh2owquBXu"
        },
        "artists": [
          {
            "external_urls": {
              "spotify": "https://open.spotify.com/artist/4gvjmrtzydbMpyJaXUtwvP"
            },
            "href": "https://api.spotify.com/v1/artists/4gvjmrtzydbMpyJaXUtwvP",
            "id": "4gvjmrtzydbMpyJaXUtwvP",
            "name": "Addison Rae",
            "type": "artist",
            "uri": "spotify:artist:4gvjmrtzydbMpyJaXUtwvP"
          }
        ],
        "available_markets": [
          "AR",
          "AU",
          "AT",
          "BE",
          "BO",
          "BR",
          "BG",
          "CA",
          "CL",
          "CO",
          "CR",
          "CY",
          "CZ",
          "DK",
          "DO",
          "DE",
          "EC",
          "EE",
          "SV",
          "FI",
          "FR",
          "GR",
          "GT",
          "HN",
          "HK",
          "HU",
          "IS",
          "IE",
          "IT",
          "LV",
          "LT",
          "LU",
          "MY",
          "MT",
          "MX",
          "NL",
          "NZ",
          "NI",
          "NO",
          "PA",
          "PY",
          "PE",
          "PH",
          "PL",
          "PT",
          "SG",
          "SK",
          "ES",
          "SE",
          "CH",
          "TW",
          "TR",
          "UY",
          "US",
          "GB",
          "AD",
          "LI",
          "MC",
          "ID",
          "JP",
          "TH",
          "VN",
          "RO",
          "IL",
          "ZA",
          "SA",
          "AE",
          "BH",
          "QA",
          "OM",
          "KW",
          "EG",
          "MA",
          "DZ",
          "TN",
          "LB",
          "JO",
          "PS",
          "IN",
          "BY",
          "KZ",
          "MD",
          "UA",
          "AL",
          "BA",
          "HR",
          "ME",
          "MK",
          "RS",
          "SI",
          "KR",
          "BD",
          "PK",
          "LK",
          "GH",
          "KE",
          "NG",
          "TZ",
          "UG",
          "AG",
          "AM",
          "BS",
          "BB",
          "BZ",
          "BT",
          "BW",
          "BF",
          "CV",
          "CW",
          "DM",
          "FJ",
          "GM",
          "GE",
          "GD",
          "GW",
          "GY",
          "HT",
          "JM",
          "KI",
          "LS",
          "LR",
          "MW",
          "MV",
          "ML",
          "MH",
          "FM",
          "NA",
          "NR",
          "NE",
          "PW",
          "PG",
          "PR",
          "WS",
          "SM",
          "ST",
          "SN",
          "SC",
          "SL",
          "SB",
          "KN",
          "LC",
          "VC",
          "SR",
          "TL",
          "TO",
          "TT",
          "TV",
          "VU",
          "AZ",
          "BN",
          "BI",
          "KH",
          "CM",
          "TD",
          "KM",
          "GQ",
          "SZ",
          "GA",
          "GN",
          "KG",
          "LA",
          "MO",
          "MR",
          "MN",
          "NP",
          "RW",
          "TG",
          "UZ",
          "ZW",
          "BJ",
          "MG",
          "MU",
          "MZ",
          "AO",
          "CI",
          "DJ",
          "ZM",
          "CD",
          "CG",
          "IQ",
          "LY",
          "TJ",
          "VE",
          "ET",
          "XK"
        ],
        "disc_number": 1,
        "duration_ms": 169697,
        "explicit": false,
        "external_ids": {
          "isrc": "USSM12405456"
        },
        "external_urls": {
          "spotify": "https://open.spotify.com/track/6MzofobZt2dm0Kf1hTThFz"
        },
        "href": "https://api.spotify.com/v1/tracks/6MzofobZt2dm0Kf1hTThFz",
        "id": "6MzofobZt2dm0Kf1hTThFz",
        "is_local": false,
        "name": "Diet Pepsi",
        "popularity": 84,
        "preview_url": null,
        "track_number": 1,
        "type": "track",
        "uri": "spotify:track:6MzofobZt2dm0Kf1hTThFz"
      },
      "played_at": "2025-03-13T04:46:44.975Z",
      "context": {
        "href": "https://api.spotify.com/v1/playlists/5m4CQQmGnhc9GPz3WWdHuB",
        "external_urls": {
          "spotify": "https://open.spotify.com/playlist/5m4CQQmGnhc9GPz3WWdHuB"
        },
        "type": "playlist",
        "uri": "spotify:playlist:5m4CQQmGnhc9GPz3WWdHuB"
      }
    },
    {
      "track": {
        "album": {
          "album_type": "single",
          "artists": [
            {
              "external_urls": {
                "spotify": "https://open.spotify.com/artist/4gvjmrtzydbMpyJaXUtwvP"
              },
              "href": "https://api.spotify.com/v1/artists/4gvjmrtzydbMpyJaXUtwvP",
              "id": "4gvjmrtzydbMpyJaXUtwvP",
              "name": "Addison Rae",
              "type": "artist",
              "uri": "spotify:artist:4gvjmrtzydbMpyJaXUtwvP"
            }
          ],
          "available_markets": [
            "AR",
            "AU",
            "AT",
            "BE",
            "BO",
            "BR",
            "BG",
            "CA",
            "CL",
            "CO",
            "CR",
            "CY",
            "CZ",
            "DK",
            "DO",
            "DE",
            "EC",
            "EE",
            "SV",
            "FI",
            "FR",
            "GR",
            "GT",
            "HN",
            "HK",
            "HU",
            "IS",
            "IE",
            "IT",
            "LV",
            "LT",
            "LU",
            "MY",
            "MT",
            "MX",
            "NL",
            "NZ",
            "NI",
            "NO",
            "PA",
            "PY",
            "PE",
            "PH",
            "PL",
            "PT",
            "SG",
            "SK",
            "ES",
            "SE",
            "CH",
            "TW",
            "TR",
            "UY",
            "US",
            "GB",
            "AD",
            "LI",
            "MC",
            "ID",
            "JP",
            "TH",
            "VN",
            "RO",
            "IL",
            "ZA",
            "SA",
            "AE",
            "BH",
            "QA",
            "OM",
            "KW",
            "EG",
            "MA",
            "DZ",
            "TN",
            "LB",
            "JO",
            "PS",
            "IN",
            "BY",
            "KZ",
            "MD",
            "UA",
            "AL",
            "BA",
            "HR",
            "ME",
            "MK",
            "RS",
            "SI",
            "KR",
            "BD",
            "PK",
            "LK",
            "GH",
            "KE",
            "NG",
            "TZ",
            "UG",
            "AG",
            "AM",
            "BS",
            "BB",
            "BZ",
            "BT",
            "BW",
            "BF",
            "CV",
            "CW",
            "DM",
            "FJ",
            "GM",
            "GE",
            "GD",
            "GW",
            "GY",
            "HT",
            "JM",
            "KI",
            "LS",
            "LR",
            "MW",
            "MV",
            "ML",
            "MH",
            "FM",
            "NA",
            "NR",
            "NE",
            "PW",
            "PG",
            "PR",
            "WS",
            "SM",
            "ST",
            "SN",
            "SC",
            "SL",
            "SB",
            "KN",
            "LC",
            "VC",
            "SR",
            "TL",
            "TO",
            "TT",
            "TV",
            "VU",
            "AZ",
            "BN",
            "BI",
            "KH",
            "CM",
            "TD",
            "KM",
            "GQ",
            "SZ",
            "GA",
            "GN",
            "KG",
            "LA",
            "MO",
            "MR",
            "MN",
            "NP",
            "RW",
            "TG",
            "UZ",
            "ZW",
            "BJ",
            "MG",
            "MU",
            "MZ",
            "AO",
            "CI",
            "DJ",
            "ZM",
            "CD",
            "CG",
            "IQ",
            "LY",
            "TJ",
            "VE",
            "ET",
            "XK"
          ],
          "external_urls": {
            "spotify": "https://open.spotify.com/album/0XA403JTounqFh2owquBXu"
          },
          "href": "https://api.spotify.com/v1/albums/0XA403JTounqFh2owquBXu",
          "id": "0XA403JTounqFh2owquBXu",
          "images": [
            {
              "height": 640,
              "url": "https://i.scdn.co/image/ab67616d0000b2734e5a5862355a5e953549292b",
              "width": 640
            },
            {
              "height": 300,
              "url": "https://i.scdn.co/image/ab67616d00001e024e5a5862355a5e953549292b",
              "width": 300
            },
            {
              "height": 64,
              "url": "https://i.scdn.co/image/ab67616d000048514e5a5862355a5e953549292b",
              "width": 64
            }
          ],
          "name": "Diet Pepsi",
          "release_date": "2024-08-09",
          "release_date_precision": "day",
          "total_tracks": 1,
          "type": "album",
          "uri": "spotify:album:0XA403JTounqFh2owquBXu"
        },
        "artists": [
          {
            "external_urls": {
              "spotify": "https://open.spotify.com/artist/4gvjmrtzydbMpyJaXUtwvP"
            },
            "href": "https://api.spotify.com/v1/artists/4gvjmrtzydbMpyJaXUtwvP",
            "id": "4gvjmrtzydbMpyJaXUtwvP",
            "name": "Addison Rae",
            "type": "artist",
            "uri": "spotify:artist:4gvjmrtzydbMpyJaXUtwvP"
          }
        ],
        "available_markets": [
          "AR",
          "AU",
          "AT",
          "BE",
          "BO",
          "BR",
          "BG",
          "CA",
          "CL",
          "CO",
          "CR",
          "CY",
          "CZ",
          "DK",
          "DO",
          "DE",
          "EC",
          "EE",
          "SV",
          "FI",
          "FR",
          "GR",
          "GT",
          "HN",
          "HK",
          "HU",
          "IS",
          "IE",
          "IT",
          "LV",
          "LT",
          "LU",
          "MY",
          "MT",
          "MX",
          "NL",
          "NZ",
          "NI",
          "NO",
          "PA",
          "PY",
          "PE",
          "PH",
          "PL",
          "PT",
          "SG",
          "SK",
          "ES",
          "SE",
          "CH",
          "TW",
          "TR",
          "UY",
          "US",
          "GB",
          "AD",
          "LI",
          "MC",
          "ID",
          "JP",
          "TH",
          "VN",
          "RO",
          "IL",
          "ZA",
          "SA",
          "AE",
          "BH",
          "QA",
          "OM",
          "KW",
          "EG",
          "MA",
          "DZ",
          "TN",
          "LB",
          "JO",
          "PS",
          "IN",
          "BY",
          "KZ",
          "MD",
          "UA",
          "AL",
          "BA",
          "HR",
          "ME",
          "MK",
          "RS",
          "SI",
          "KR",
          "BD",
          "PK",
          "LK",
          "GH",
          "KE",
          "NG",
          "TZ",
          "UG",
          "AG",
          "AM",
          "BS",
          "BB",
          "BZ",
          "BT",
          "BW",
          "BF",
          "CV",
          "CW",
          "DM",
          "FJ",
          "GM",
          "GE",
          "GD",
          "GW",
          "GY",
          "HT",
          "JM",
          "KI",
          "LS",
          "LR",
          "MW",
          "MV",
          "ML",
          "MH",
          "FM",
          "NA",
          "NR",
          "NE",
          "PW",
          "PG",
          "PR",
          "WS",
          "SM",
          "ST",
          "SN",
          "SC",
          "SL",
          "SB",
          "KN",
          "LC",
          "VC",
          "SR",
          "TL",
          "TO",
          "TT",
          "TV",
          "VU",
          "AZ",
          "BN",
          "BI",
          "KH",
          "CM",
          "TD",
          "KM",
          "GQ",
          "SZ",
          "GA",
          "GN",
          "KG",
          "LA",
          "MO",
          "MR",
          "MN",
          "NP",
          "RW",
          "TG",
          "UZ",
          "ZW",
          "BJ",
          "MG",
          "MU",
          "MZ",
          "AO",
          "CI",
          "DJ",
          "ZM",
          "CD",
          "CG",
          "IQ",
          "LY",
          "TJ",
          "VE",
          "ET",
          "XK"
        ],
        "disc_number": 1,
        "duration_ms": 169697,
        "explicit": false,
        "external_ids": {
          "isrc": "USSM12405456"
        },
        "external_urls": {
          "spotify": "https://open.spotify.com/track/6MzofobZt2dm0Kf1hTThFz"
        },
        "href": "https://api.spotify.com/v1/tracks/6MzofobZt2dm0Kf1hTThFz",
        "id": "6MzofobZt2dm0Kf1hTThFz",
        "is_local": false,
        "name": "Diet Pepsi",
        "popularity": 84,
        "preview_url": null,
        "track_number": 1,
        "type": "track",
        "uri": "spotify:track:6MzofobZt2dm0Kf1hTThFz"
      },
      "played_at": "2025-03-13T04:51:29.320Z",
      "context": {
        "type": "playlist",
        "external_urls": {
          "spotify": "https://open.spotify.com/playlist/5m4CQQmGnhc9GPz3WWdHuB"
        },
        "href": "https://api.spotify.com/v1/playlists/5m4CQQmGnhc9GPz3WWdHuB",
        "uri": "spotify:playlist:5m4CQQmGnhc9GPz3WWdHuB"
      }
    },
    {
      "track": {
        "album": {
          "album_type": "album",
          "artists": [
            {
              "external_urls": {
                "spotify": "https://open.spotify.com/artist/7tYKF4w9nC0nq9CsPZTHyP"
              },
              "href": "https://api.spotify.com/v1/artists/7tYKF4w9nC0nq9CsPZTHyP",
              "id": "7tYKF4w9nC0nq9CsPZTHyP",
              "name": "SZA",
              "type": "artist",
              "uri": "spotify:artist:7tYKF4w9nC0nq9CsPZTHyP"
            }
          ],
          "available_markets": [
            "AR",
            "AU",
            "AT",
            "BE",
            "BO",
            "BR",
            "BG",
            "CA",
            "CL",
            "CO",
            "CR",
            "CY",
            "CZ",
            "DK",
            "DO",
            "DE",
            "EC",
            "EE",
            "SV",
            "FI",
            "FR",
            "GR",
            "GT",
            "HN",
            "HK",
            "HU",
            "IS",
            "IE",
            "IT",
            "LV",
            "LT",
            "LU",
            "MY",
            "MT",
            "MX",
            "NL",
            "NZ",
            "NI",
            "NO",
            "PA",
            "PY",
            "PE",
            "PH",
            "PL",
            "PT",
            "SG",
            "SK",
            "ES",
            "SE",
            "CH",
            "TW",
            "TR",
            "UY",
            "US",
            "GB",
            "AD",
            "LI",
            "MC",
            "ID",
            "JP",
            "TH",
            "VN",
            "RO",
            "IL",
            "ZA",
            "SA",
            "AE",
            "BH",
            "QA",
            "OM",
            "KW",
            "EG",
            "MA",
            "DZ",
            "TN",
            "LB",
            "JO",
            "PS",
            "IN",
            "BY",
            "KZ",
            "MD",
            "UA",
            "AL",
            "BA",
            "HR",
            "ME",
            "MK",
            "RS",
            "SI",
            "KR",
            "BD",
            "PK",
            "LK",
            "GH",
            "KE",
            "NG",
            "TZ",
            "UG",
            "AG",
            "AM",
            "BS",
            "BB",
            "BZ",
            "BT",
            "BW",
            "BF",
            "CV",
            "CW",
            "DM",
            "FJ",
            "GM",
            "GE",
            "GD",
            "GW",
            "GY",
            "HT",
            "JM",
            "KI",
            "LS",
            "LR",
            "MW",
            "MV",
            "ML",
            "MH",
            "FM",
            "NA",
            "NR",
            "NE",
            "PW",
            "PG",
            "PR",
            "WS",
            "SM",
            "ST",
            "SN",
            "SC",
            "SL",
            "SB",
            "KN",
            "LC",
            "VC",
            "SR",
            "TL",
            "TO",
            "TT",
            "TV",
            "VU",
            "AZ",
            "BN",
            "BI",
            "KH",
            "CM",
            "TD",
            "KM",
            "GQ",
            "SZ",
            "GA",
            "GN",
            "KG",
            "LA",
            "MO",
            "MR",
            "MN",
            "NP",
            "RW",
            "TG",
            "UZ",
            "ZW",
            "BJ",
            "MG",
            "MU",
            "MZ",
            "AO",
            "CI",
            "DJ",
            "ZM",
            "CD",
            "CG",
            "IQ",
            "LY",
            "TJ",
            "VE",
            "ET",
            "XK"
          ],
          "external_urls": {
            "spotify": "https://open.spotify.com/album/3VQkNrG74QPY4rHBPoyZYZ"
          },
          "href": "https://api.spotify.com/v1/albums/3VQkNrG74QPY4rHBPoyZYZ",
          "id": "3VQkNrG74QPY4rHBPoyZYZ",
          "images": [
            {
              "height": 640,
              "url": "https://i.scdn.co/image/ab67616d0000b2737f5a318e3ff35defa8d0e4af",
              "width": 640
            },
            {
              "height": 300,
              "url": "https://i.scdn.co/image/ab67616d00001e027f5a318e3ff35defa8d0e4af",
              "width": 300
            },
            {
              "height": 64,
              "url": "https://i.scdn.co/image/ab67616d000048517f5a318e3ff35defa8d0e4af",
              "width": 64
            }
          ],
          "name": "SOS Deluxe: LANA",
          "release_date": "2024-12-20",
          "release_date_precision": "day",
          "total_tracks": 38,
          "type": "album",
          "uri": "spotify:album:3VQkNrG74QPY4rHBPoyZYZ"
        },
        "artists": [
          {
            "external_urls": {
              "spotify": "https://open.spotify.com/artist/7tYKF4w9nC0nq9CsPZTHyP"
            },
            "href": "https://api.spotify.com/v1/artists/7tYKF4w9nC0nq9CsPZTHyP",
            "id": "7tYKF4w9nC0nq9CsPZTHyP",
            "name": "SZA",
            "type": "artist",
            "uri": "spotify:artist:7tYKF4w9nC0nq9CsPZTHyP"
          }
        ],
        "available_markets": [
          "AR",
          "AU",
          "AT",
          "BE",
          "BO",
          "BR",
          "BG",
          "CA",
          "CL",
          "CO",
          "CR",
          "CY",
          "CZ",
          "DK",
          "DO",
          "DE",
          "EC",
          "EE",
          "SV",
          "FI",
          "FR",
          "GR",
          "GT",
          "HN",
          "HK",
          "HU",
          "IS",
          "IE",
          "IT",
          "LV",
          "LT",
          "LU",
          "MY",
          "MT",
          "MX",
          "NL",
          "NZ",
          "NI",
          "NO",
          "PA",
          "PY",
          "PE",
          "PH",
          "PL",
          "PT",
          "SG",
          "SK",
          "ES",
          "SE",
          "CH",
          "TW",
          "TR",
          "UY",
          "US",
          "GB",
          "AD",
          "LI",
          "MC",
          "ID",
          "JP",
          "TH",
          "VN",
          "RO",
          "IL",
          "ZA",
          "SA",
          "AE",
          "BH",
          "QA",
          "OM",
          "KW",
          "EG",
          "MA",
          "DZ",
          "TN",
          "LB",
          "JO",
          "PS",
          "IN",
          "BY",
          "KZ",
          "MD",
          "UA",
          "AL",
          "BA",
          "HR",
          "ME",
          "MK",
          "RS",
          "SI",
          "KR",
          "BD",
          "PK",
          "LK",
          "GH",
          "KE",
          "NG",
          "TZ",
          "UG",
          "AG",
          "AM",
          "BS",
          "BB",
          "BZ",
          "BT",
          "BW",
          "BF",
          "CV",
          "CW",
          "DM",
          "FJ",
          "GM",
          "GE",
          "GD",
          "GW",
          "GY",
          "HT",
          "JM",
          "KI",
          "LS",
          "LR",
          "MW",
          "MV",
          "ML",
          "MH",
          "FM",
          "NA",
          "NR",
          "NE",
          "PW",
          "PG",
          "PR",
          "WS",
          "SM",
          "ST",
          "SN",
          "SC",
          "SL",
          "SB",
          "KN",
          "LC",
          "VC",
          "SR",
          "TL",
          "TO",
          "TT",
          "TV",
          "VU",
          "AZ",
          "BN",
          "BI",
          "KH",
          "CM",
          "TD",
          "KM",
          "GQ",
          "SZ",
          "GA",
          "GN",
          "KG",
          "LA",
          "MO",
          "MR",
          "MN",
          "NP",
          "RW",
          "TG",
          "UZ",
          "ZW",
          "BJ",
          "MG",
          "MU",
          "MZ",
          "AO",
          "CI",
          "DJ",
          "ZM",
          "CD",
          "CG",
          "IQ",
          "LY",
          "TJ",
          "VE",
          "ET",
          "XK"
        ],
        "disc_number": 1,
        "duration_ms": 167448,
        "explicit": true,
        "external_ids": {
          "isrc": "USRC12403824"
        },
        "external_urls": {
          "spotify": "https://open.spotify.com/track/6jTQijAuYxOd8DjQ8D6UkL"
        },
        "href": "https://api.spotify.com/v1/tracks/6jTQijAuYxOd8DjQ8D6UkL",
        "id": "6jTQijAuYxOd8DjQ8D6UkL",
        "is_local": false,
        "name": "What Do I Do",
        "popularity": 78,
        "preview_url": null,
        "track_number": 2,
        "type": "track",
        "uri": "spotify:track:6jTQijAuYxOd8DjQ8D6UkL"
      },
      "played_at": "2025-03-13T04:54:16.850Z",
      "context": {
        "type": "playlist",
        "external_urls": {
          "spotify": "https://open.spotify.com/playlist/5m4CQQmGnhc9GPz3WWdHuB"
        },
        "href": "https://api.spotify.com/v1/playlists/5m4CQQmGnhc9GPz3WWdHuB",
        "uri": "spotify:playlist:5m4CQQmGnhc9GPz3WWdHuB"
      }
    },
    {
      "track": {
        "album": {
          "album_type": "single",
          "artists": [
            {
              "external_urls": {
                "spotify": "https://open.spotify.com/artist/5L1lO4eRHmJ7a0Q6csE5cT"
              },
              "href": "https://api.spotify.com/v1/artists/5L1lO4eRHmJ7a0Q6csE5cT",
              "id": "5L1lO4eRHmJ7a0Q6csE5cT",
              "name": "LISA",
              "type": "artist",
              "uri": "spotify:artist:5L1lO4eRHmJ7a0Q6csE5cT"
            }
          ],
          "available_markets": [
            "AR",
            "AU",
            "AT",
            "BE",
            "BO",
            "BR",
            "BG",
            "CA",
            "CL",
            "CO",
            "CR",
            "CY",
            "CZ",
            "DK",
            "DO",
            "DE",
            "EC",
            "EE",
            "SV",
            "FI",
            "FR",
            "GR",
            "GT",
            "HN",
            "HK",
            "HU",
            "IS",
            "IE",
            "IT",
            "LV",
            "LT",
            "LU",
            "MY",
            "MT",
            "MX",
            "NL",
            "NZ",
            "NI",
            "NO",
            "PA",
            "PY",
            "PE",
            "PH",
            "PL",
            "PT",
            "SG",
            "SK",
            "ES",
            "CH",
            "TW",
            "TR",
            "UY",
            "US",
            "GB",
            "AD",
            "LI",
            "MC",
            "ID",
            "JP",
            "TH",
            "VN",
            "RO",
            "IL",
            "ZA",
            "SA",
            "AE",
            "BH",
            "QA",
            "OM",
            "KW",
            "EG",
            "MA",
            "DZ",
            "TN",
            "LB",
            "JO",
            "PS",
            "IN",
            "BY",
            "KZ",
            "MD",
            "UA",
            "AL",
            "BA",
            "HR",
            "ME",
            "MK",
            "RS",
            "SI",
            "KR",
            "BD",
            "PK",
            "LK",
            "GH",
            "KE",
            "NG",
            "TZ",
            "UG",
            "AG",
            "AM",
            "BS",
            "BB",
            "BZ",
            "BT",
            "BW",
            "BF",
            "CV",
            "CW",
            "DM",
            "FJ",
            "GM",
            "GE",
            "GD",
            "GW",
            "GY",
            "HT",
            "JM",
            "KI",
            "LS",
            "LR",
            "MW",
            "MV",
            "ML",
            "MH",
            "FM",
            "NA",
            "NR",
            "NE",
            "PW",
            "PG",
            "PR",
            "WS",
            "SM",
            "ST",
            "SN",
            "SC",
            "SL",
            "SB",
            "KN",
            "LC",
            "VC",
            "SR",
            "TL",
            "TO",
            "TT",
            "TV",
            "VU",
            "AZ",
            "BN",
            "BI",
            "KH",
            "CM",
            "TD",
            "KM",
            "GQ",
            "SZ",
            "GA",
            "GN",
            "KG",
            "LA",
            "MO",
            "MR",
            "MN",
            "NP",
            "RW",
            "TG",
            "UZ",
            "ZW",
            "BJ",
            "MG",
            "MU",
            "MZ",
            "AO",
            "CI",
            "DJ",
            "ZM",
            "CD",
            "CG",
            "IQ",
            "LY",
            "TJ",
            "VE",
            "ET",
            "XK"
          ],
          "external_urls": {
            "spotify": "https://open.spotify.com/album/2F84s5tvr9RSS6VI772mVb"
          },
          "href": "https://api.spotify.com/v1/albums/2F84s5tvr9RSS6VI772mVb",
          "id": "2F84s5tvr9RSS6VI772mVb",
          "images": [
            {
              "height": 640,
              "url": "https://i.scdn.co/image/ab67616d0000b2735a039ed450d3e9a5caaf7818",
              "width": 640
            },
            {
              "height": 300,
              "url": "https://i.scdn.co/image/ab67616d00001e025a039ed450d3e9a5caaf7818",
              "width": 300
            },
            {
              "height": 64,
              "url": "https://i.scdn.co/image/ab67616d000048515a039ed450d3e9a5caaf7818",
              "width": 64
            }
          ],
          "name": "Moonlit Floor (Kiss Me)",
          "release_date": "2024-10-03",
          "release_date_precision": "day",
          "total_tracks": 1,
          "type": "album",
          "uri": "spotify:album:2F84s5tvr9RSS6VI772mVb"
        },
        "artists": [
          {
            "external_urls": {
              "spotify": "https://open.spotify.com/artist/5L1lO4eRHmJ7a0Q6csE5cT"
            },
            "href": "https://api.spotify.com/v1/artists/5L1lO4eRHmJ7a0Q6csE5cT",
            "id": "5L1lO4eRHmJ7a0Q6csE5cT",
            "name": "LISA",
            "type": "artist",
            "uri": "spotify:artist:5L1lO4eRHmJ7a0Q6csE5cT"
          }
        ],
        "available_markets": [
          "AR",
          "AU",
          "AT",
          "BE",
          "BO",
          "BR",
          "BG",
          "CA",
          "CL",
          "CO",
          "CR",
          "CY",
          "CZ",
          "DK",
          "DO",
          "DE",
          "EC",
          "EE",
          "SV",
          "FI",
          "FR",
          "GR",
          "GT",
          "HN",
          "HK",
          "HU",
          "IS",
          "IE",
          "IT",
          "LV",
          "LT",
          "LU",
          "MY",
          "MT",
          "MX",
          "NL",
          "NZ",
          "NI",
          "NO",
          "PA",
          "PY",
          "PE",
          "PH",
          "PL",
          "PT",
          "SG",
          "SK",
          "ES",
          "CH",
          "TW",
          "TR",
          "UY",
          "US",
          "GB",
          "AD",
          "LI",
          "MC",
          "ID",
          "JP",
          "TH",
          "VN",
          "RO",
          "IL",
          "ZA",
          "SA",
          "AE",
          "BH",
          "QA",
          "OM",
          "KW",
          "EG",
          "MA",
          "DZ",
          "TN",
          "LB",
          "JO",
          "PS",
          "IN",
          "BY",
          "KZ",
          "MD",
          "UA",
          "AL",
          "BA",
          "HR",
          "ME",
          "MK",
          "RS",
          "SI",
          "KR",
          "BD",
          "PK",
          "LK",
          "GH",
          "KE",
          "NG",
          "TZ",
          "UG",
          "AG",
          "AM",
          "BS",
          "BB",
          "BZ",
          "BT",
          "BW",
          "BF",
          "CV",
          "CW",
          "DM",
          "FJ",
          "GM",
          "GE",
          "GD",
          "GW",
          "GY",
          "HT",
          "JM",
          "KI",
          "LS",
          "LR",
          "MW",
          "MV",
          "ML",
          "MH",
          "FM",
          "NA",
          "NR",
          "NE",
          "PW",
          "PG",
          "PR",
          "WS",
          "SM",
          "ST",
          "SN",
          "SC",
          "SL",
          "SB",
          "KN",
          "LC",
          "VC",
          "SR",
          "TL",
          "TO",
          "TT",
          "TV",
          "VU",
          "AZ",
          "BN",
          "BI",
          "KH",
          "CM",
          "TD",
          "KM",
          "GQ",
          "SZ",
          "GA",
          "GN",
          "KG",
          "LA",
          "MO",
          "MR",
          "MN",
          "NP",
          "RW",
          "TG",
          "UZ",
          "ZW",
          "BJ",
          "MG",
          "MU",
          "MZ",
          "AO",
          "CI",
          "DJ",
          "ZM",
          "CD",
          "CG",
          "IQ",
          "LY",
          "TJ",
          "VE",
          "ET",
          "XK"
        ],
        "disc_number": 1,
        "duration_ms": 155757,
        "explicit": false,
        "external_ids": {
          "isrc": "USRC12402958"
        },
        "external_urls": {
          "spotify": "https://open.spotify.com/track/3yDRcs0Y4pPzkvMbUfeF9H"
        },
        "href": "https://api.spotify.com/v1/tracks/3yDRcs0Y4pPzkvMbUfeF9H",
        "id": "3yDRcs0Y4pPzkvMbUfeF9H",
        "is_local": false,
        "name": "Moonlit Floor (Kiss Me)",
        "popularity": 80,
        "preview_url": null,
        "track_number": 1,
        "type": "track",
        "uri": "spotify:track:3yDRcs0Y4pPzkvMbUfeF9H"
      },
      "played_at": "2025-03-13T04:56:52.539Z",
      "context": {
        "type": "playlist",
        "external_urls": {
          "spotify": "https://open.spotify.com/playlist/5m4CQQmGnhc9GPz3WWdHuB"
        },
        "href": "https://api.spotify.com/v1/playlists/5m4CQQmGnhc9GPz3WWdHuB",
        "uri": "spotify:playlist:5m4CQQmGnhc9GPz3WWdHuB"
      }
    }
  ]
}